serial_y_cable.py
serial_y_cable-0.2.0.dist-info/METADATA
serial_y_cable-0.2.0.dist-info/WHEEL
serial_y_cable-0.2.0.dist-info/entry_points.txt
serial_y_cable-0.2.0.dist-info/licenses/LICENSE
serial_y_cable-0.2.0.dist-info/RECORD
