Metadata-Version: 2.1
Name: serial_y_cable
Version: 0.2.0
Summary: The serial_y_cable Tool
Project-URL: Homepage, https://github.com/chriesibaum/serial_y_cable
Author-email: Thomas <thomas@chriesibaum.com>
License: tbd.
License-File: LICENSE
Classifier: License :: OSI Approved :: MIT License
Classifier: Operating System :: OS Independent
Classifier: Programming Language :: Python :: 3
Requires-Python: >=3.8
Requires-Dist: key-stroke
Requires-Dist: pyserial
